msa4u/__init__.py
msa4u/drawing.py
msa4u/manager.py
msa4u/methods.py
msa4u/msa4u_data/.DS_Store
msa4u/msa4u_data/aa_sequences.fa
msa4u/msa4u_data/colors_aa.txt
msa4u/msa4u_data/colors_nt.txt
msa4u/msa4u_data/help.txt
msa4u/msa4u_data/palette.txt
msa4u/msa4u_data/standard.cfg
msa4u/msa4u_data/bin/.DS_Store
msa4u/msa4u_data/bin/mafft-linux64/.DS_Store
msa4u/msa4u_data/bin/mafft-linux64/mafft.bat
msa4u/msa4u_data/bin/mafft-linux64/mafftdir/.DS_Store
msa4u/msa4u_data/bin/mafft-linux64/mafftdir/bin/mafft
msa4u/msa4u_data/bin/mafft-linux64/mafftdir/libexec/addsingle
msa4u/msa4u_data/bin/mafft-linux64/mafftdir/libexec/contrafoldwrap
msa4u/msa4u_data/bin/mafft-linux64/mafftdir/libexec/countlen
msa4u/msa4u_data/bin/mafft-linux64/mafftdir/libexec/dash_alignments
msa4u/msa4u_data/bin/mafft-linux64/mafftdir/libexec/dash_client
msa4u/msa4u_data/bin/mafft-linux64/mafftdir/libexec/dash_sequences.fa
msa4u/msa4u_data/bin/mafft-linux64/mafftdir/libexec/disttbfast
msa4u/msa4u_data/bin/mafft-linux64/mafftdir/libexec/dndblast
msa4u/msa4u_data/bin/mafft-linux64/mafftdir/libexec/dndfast7
msa4u/msa4u_data/bin/mafft-linux64/mafftdir/libexec/dndpre
msa4u/msa4u_data/bin/mafft-linux64/mafftdir/libexec/dvtditr
msa4u/msa4u_data/bin/mafft-linux64/mafftdir/libexec/f2cl
msa4u/msa4u_data/bin/mafft-linux64/mafftdir/libexec/filter
msa4u/msa4u_data/bin/mafft-linux64/mafftdir/libexec/getlag
msa4u/msa4u_data/bin/mafft-linux64/mafftdir/libexec/hat3
msa4u/msa4u_data/bin/mafft-linux64/mafftdir/libexec/hex2maffttext
msa4u/msa4u_data/bin/mafft-linux64/mafftdir/libexec/mafft-distance
msa4u/msa4u_data/bin/mafft-linux64/mafftdir/libexec/mafft-homologs.1
msa4u/msa4u_data/bin/mafft-linux64/mafftdir/libexec/mafft-profile
msa4u/msa4u_data/bin/mafft-linux64/mafftdir/libexec/mafft.1
msa4u/msa4u_data/bin/mafft-linux64/mafftdir/libexec/mafftash_premafft.pl
msa4u/msa4u_data/bin/mafft-linux64/mafftdir/libexec/maffttext2hex
msa4u/msa4u_data/bin/mafft-linux64/mafftdir/libexec/makedirectionlist
msa4u-0.4.0.dist-info/LICENSE
msa4u-0.4.0.dist-info/LICENSE_dependencies
msa4u-0.4.0.dist-info/METADATA
msa4u-0.4.0.dist-info/WHEEL
msa4u-0.4.0.dist-info/top_level.txt
msa4u-0.4.0.dist-info/RECORD
