Metadata-Version: 2.1
Name: msa4u
Version: 0.4.0
Summary: A tool for short uORF annotation.
Home-page: https://art-egorov.github.io/msa4u/
Author: Artyom Egorov
Author-email: artem.egorov@med.lu.se
License: WTFPL
License-File: LICENSE
License-File: LICENSE_dependencies
Requires-Dist: biopython
Requires-Dist: configs
Requires-Dist: argparse
Requires-Dist: statistics
Requires-Dist: pandas
Requires-Dist: reportlab
